{
  "gripper": {
    "0": {
      "A": 400,
      "B": 1100,
      "C": 1785,
      "D": 2420
    },
    "2": {
      "A": 400,
      "B": 1040,
      "C": 1710,
      "D": 2400
    },
    "6": {
      "A": 475,
      "B": 1120,
      "C": 1800,
      "D": 2425
    },
    "8": {
      "A": 450,
      "B": 1120,
      "C": 1810,
      "D": 2425
    }
  },
  "rp": {
    "1": {
      "retracted": 1890,
      "hold": 1055
    },
    "3": {
      "retracted": 1815,
      "hold": 1100
    },
    "7": {
      "retracted": 1875,
      "hold": 990
    },
    "9": {
      "retracted": 1880,
      "hold": 1100
    }
  }
}
